pymyorm/__init__.py
pymyorm/batch.py
pymyorm/connection_pool.py
pymyorm/database.py
pymyorm/local.py
pymyorm/model.py
pymyorm/singleton.py
pymyorm/transaction.py
pymyorm/driver/__init__.py
pymyorm/driver/mysql.py
tests/__init__.py
tests/config.py
tests/my_admin.py
tests/my_average.py
tests/my_average_join.py
tests/my_batch.py
tests/my_between.py
tests/my_column.py
tests/my_column_join.py
tests/my_count.py
tests/my_count_join.py
tests/my_date.py
tests/my_delete.py
tests/my_dict.py
tests/my_exists.py
tests/my_exists_join.py
tests/my_group.py
tests/my_group_count.py
tests/my_having.py
tests/my_insert.py
tests/my_insert_batch.py
tests/my_join.py
tests/my_max.py
tests/my_max_join.py
tests/my_min.py
tests/my_min_join.py
tests/my_null.py
tests/my_ping.py
tests/my_pool.py
tests/my_query.py
tests/my_raw.py
tests/my_reflect.py
tests/my_savepoint.py
tests/my_scalar.py
tests/my_scalar_join.py
tests/my_schema.py
tests/my_select.py
tests/my_select_group.py
tests/my_select_join.py
tests/my_shop.py
tests/my_sum.py
tests/my_table_create.py
tests/my_table_exists.py
tests/my_table_key.py
tests/my_table_show.py
tests/my_truncate.py
tests/my_trx.py
tests/my_trx_func.py
tests/my_trx_loop.py
tests/my_update.py
tests/my_where.py
tests/models/__init__.py
tests/models/admin.py
tests/models/admin_auth.py
tests/models/admin_role.py
tests/models/shop.py
tests/models/user.py
PyMyORM-2.0.2.dist-info/LICENSE
PyMyORM-2.0.2.dist-info/METADATA
PyMyORM-2.0.2.dist-info/WHEEL
PyMyORM-2.0.2.dist-info/top_level.txt
PyMyORM-2.0.2.dist-info/RECORD
